rer/__init__.py
rer-1.1.2.dist-info/DESCRIPTION.rst
rer-1.1.2.dist-info/METADATA
rer-1.1.2.dist-info/RECORD
rer-1.1.2.dist-info/WHEEL
rer-1.1.2.dist-info/metadata.json
rer-1.1.2.dist-info/top_level.txt
