Metadata-Version: 2.0
Name: rer
Version: 1.1.2
Summary: Regular expression in regular expression
Home-page: https://github.com/jks-liu/rere
Author: Meme Kagurazaka
Author-email: github@mrliu.org
License: Public Domain
Keywords: Nested regular expression re
Platform: UNKNOWN
Classifier: Development Status :: 5 - Production/Stable
Classifier: Intended Audience :: Developers
Classifier: Topic :: Software Development :: Libraries
Classifier: License :: Public Domain
Classifier: Programming Language :: Python :: 2
Classifier: Programming Language :: Python :: 2.7
Classifier: Programming Language :: Python :: 3
Classifier: Programming Language :: Python :: 3.5
Classifier: Programming Language :: Python :: 3.6
